.DS_Store
Codexes2Gemini/.DS_Store
Codexes2Gemini/__init__.py
Codexes2Gemini/toy_bisac_merger.py
Codexes2Gemini/classes/__init__.py
Codexes2Gemini/classes/user_space.py
Codexes2Gemini/classes/ADEPT/ADEPT_Multiple_File_Self_Serve.py
Codexes2Gemini/classes/ADEPT/ADEPT_Multiple_Utilities.py
Codexes2Gemini/classes/ADEPT/ADEPT_Single_File_Self_Serve.py
Codexes2Gemini/classes/ADEPT/ADEPT_headless_multiple_build.py
Codexes2Gemini/classes/ADEPT/ADEPT_utilities.py
Codexes2Gemini/classes/ADEPT/BulkPDFProcessor.py
Codexes2Gemini/classes/ADEPT/CorePDFProcessor.py
Codexes2Gemini/classes/ADEPT/SinglePDFProcessor.py
Codexes2Gemini/classes/ADEPT/__init__.py
Codexes2Gemini/classes/ADEPT/data.json
Codexes2Gemini/classes/ADEPT/escobar_series.md
Codexes2Gemini/classes/ADEPT/metadatas2bookjson.py
Codexes2Gemini/classes/ADEPT/scratchbulkpdf.py
Codexes2Gemini/classes/ADEPT/socialsecurity.md
Codexes2Gemini/classes/ADEPT/specials
Codexes2Gemini/classes/ADEPT/tes.json
Codexes2Gemini/classes/ADEPT/toy-scrapy.py
Codexes2Gemini/classes/ADEPT/toy_single_pdf.py
Codexes2Gemini/classes/ADEPT/toy_st.py
Codexes2Gemini/classes/Codexes/__init__.py
Codexes2Gemini/classes/Codexes/Builders/BuildLauncher.py
Codexes2Gemini/classes/Codexes/Builders/CSV2PromptPlan.py
Codexes2Gemini/classes/Codexes/Builders/CSV2PromptTemplate.csv
Codexes2Gemini/classes/Codexes/Builders/CodexBuilder.py
Codexes2Gemini/classes/Codexes/Builders/Codexes2Codexes.py
Codexes2Gemini/classes/Codexes/Builders/Codexes2PartsOfTheBook.py
Codexes2Gemini/classes/Codexes/Builders/MultiContextBuilder.py
Codexes2Gemini/classes/Codexes/Builders/PartsBuilder.py
Codexes2Gemini/classes/Codexes/Builders/PromptGroups.py
Codexes2Gemini/classes/Codexes/Builders/PromptsPlan.py
Codexes2Gemini/classes/Codexes/Builders/Responses2PromptsPlan.py
Codexes2Gemini/classes/Codexes/Builders/__init__.py
Codexes2Gemini/classes/Codexes/Builders/collapsar_classics.py
Codexes2Gemini/classes/Codexes/Builders/convert_json_to_markdown.py
Codexes2Gemini-0.5.0.0.dist-info/LICENSE
Codexes2Gemini-0.5.0.0.dist-info/METADATA
Codexes2Gemini-0.5.0.0.dist-info/WHEEL
Codexes2Gemini-0.5.0.0.dist-info/entry_points.txt
Codexes2Gemini-0.5.0.0.dist-info/top_level.txt
Codexes2Gemini-0.5.0.0.dist-info/RECORD
