Metadata-Version: 2.1
Name: Codexes2Gemini
Version: 0.5.0.0
Summary: Humans and AIs making books richer, more diverse, and more surprising.
Home-page: https://github.com/fredzannarbor/Codexes2Gemini
Author: Fred_Zimmerman
Author-email: wfz@nimblebooks.com
License: MIT
Classifier: Development Status :: 3 - Alpha
Classifier: Intended Audience :: Developers
Classifier: Topic :: Software Development :: Build Tools
Classifier: License :: OSI Approved :: MIT License
Classifier: Programming Language :: Python :: 3
Classifier: Programming Language :: Python :: 3.11
Requires-Python: >=3.11
License-File: LICENSE
Requires-Dist: streamlit
Requires-Dist: pymupdf
Requires-Dist: pypandoc
Requires-Dist: python-docx
Requires-Dist: google-generativeai
Requires-Dist: docx2txt
Requires-Dist: chardet
